Metadata-Version: 2.1
Name: Swarm-ECS
Version: 1.0.0.2024.post1
Summary: A Flexible Light-Weight Object-Oriented ECS
Home-page: https://github.com/Zero-th/Swarm
Author: Izaiyah Stokes
Author-email: zeroth.bat@gmail.com
Classifier: Programming Language :: Python :: 3.12
Classifier: License :: OSI Approved :: Apache Software License
Classifier: Operating System :: OS Independent
License-File: LICENSE
